LICENSE.txt
evo_bridge_websocket/__init__.py
evo_bridge_websocket/automation/api.yaml
evo_bridge_websocket/automation/entity.yaml
evo_bridge_websocket/automation/tests.yaml
evo_bridge_websocket/utility/IuWebsocket.py
evo_bridge_websocket/utility/UWebsocket.py
evo_bridge_websocket/utility/__init__.py
evo_bridge_websocket-2024.10.22325.dist-info/LICENSE.txt
evo_bridge_websocket-2024.10.22325.dist-info/METADATA
evo_bridge_websocket-2024.10.22325.dist-info/WHEEL
evo_bridge_websocket-2024.10.22325.dist-info/RECORD
