Metadata-Version: 2.1
Name: evo-bridge-websocket
Version: 2024.10.22325
Summary: evo-bridge-websocket python
License: CC BY-NC-ND 4.0
Author: cyborg-ai-git
Author-email: 129898917+cyborg-ai-git@users.noreply.github.com
Requires-Python: >=3.10,<4.0
Classifier: License :: Other/Proprietary License
Classifier: Programming Language :: Python :: 3
Classifier: Programming Language :: Python :: 3.10
Classifier: Programming Language :: Python :: 3.11
Classifier: Programming Language :: Python :: 3.12
Requires-Dist: evo-framework (>=2024.5.28,<2025.0.0)
